qb_gen/Password.py
qb_gen/__init__.py
qb_gen/__main__.py
qb_gen/cli.py
qb_gen/cli_helpers.py
qb_gen/constants.py
qb_gen/utils.py
tests/__init__.py
tests/test_generator.py
tests/test_generator_from_input.py
tests/test_validation.py
QB_gen-0.0.2.dist-info/METADATA
QB_gen-0.0.2.dist-info/WHEEL
QB_gen-0.0.2.dist-info/top_level.txt
QB_gen-0.0.2.dist-info/RECORD
