Metadata-Version: 2.1
Name: QB-gen
Version: 0.0.2
Summary: Password validator and generator CLI tool.
Home-page: https://github.com/NgoQuocBao1010/QB-generator
Author: Ngo Hong Quoc Bao
Author-email: quocbao.ngoh@gmail.com
License: UNKNOWN
Platform: UNKNOWN
Classifier: Development Status :: 4 - Beta
Classifier: Intended Audience :: Developers
Classifier: License :: OSI Approved :: MIT License
Classifier: Programming Language :: Python :: 3.9
Classifier: Operating System :: MacOS
Requires-Python: >=3.9
Requires-Dist: typer (==0.7.0)
Requires-Dist: rich (==12.6.0)
Requires-Dist: Unidecode (==1.3.6)
